LICENSE
README.md
setup.cfg
setup.py
data/icarus/inc/dump.vh
data/icarus/src/dump.v
src/pueda/__init__.py
src/pueda/common.py
src/pueda/edalize.py
src/pueda/gtkw.py
src/pueda/icarus.py
src/pueda/myhdl.py
src/pueda/pyverilator.py
src/pueda/vcd.py
src/pueda/veriloggen.py
src/pueda/yosys.py
src/pueda.egg-info/PKG-INFO
src/pueda.egg-info/SOURCES.txt
src/pueda.egg-info/dependency_links.txt
src/pueda.egg-info/requires.txt
src/pueda.egg-info/top_level.txt
test/test.py
test/test_myhdl_counter.py
test/test_verilated_dpi_counter.py
test/test_verilator_counter.py