Metadata-Version: 2.1
Name: pueda
Version: 0.1.10
Summary: Collection of python for micro-Electronic Design Automation
Home-page: https://github.com/bat52/pueda
Author: Marco Merlin
Author-email: marcomerli@gmail.com
License: Apache 2.0
Keywords: python EDA CAD
Platform: UNKNOWN
License-File: LICENSE
